damask/LICENSE
damask/VERSION
damask/__init__.py
damask/_colormap.py
damask/_configmaterial.py
damask/_crystal.py
damask/_geomgrid.py
damask/_loadcasegrid.py
damask/_orientation.py
damask/_result.py
damask/_rotation.py
damask/_table.py
damask/_typehints.py
damask/_vtk.py
damask/_yaml.py
damask/grid_filters.py
damask/mechanics.py
damask/seeds.py
damask/tensor.py
damask/util.py
damask/solver/__init__.py
damask/solver/_marc.py
damask-3.0.2.dist-info/METADATA
damask-3.0.2.dist-info/WHEEL
damask-3.0.2.dist-info/top_level.txt
damask-3.0.2.dist-info/RECORD
