Metadata-Version: 2.4
Name: damask
Version: 3.0.2
Summary: DAMASK processing tools
Home-page: https://damask.mpie.de
Author: The DAMASK team
Author-email: damask@mpie.de
License: AGPL3
Classifier: Intended Audience :: Science/Research
Classifier: Topic :: Scientific/Engineering
Classifier: Programming Language :: Python :: 3
Classifier: License :: OSI Approved :: GNU Affero General Public License v3 or later (AGPLv3+)
Classifier: Operating System :: OS Independent
Requires-Python: >=3.8
Requires-Dist: pandas>=0.24
Requires-Dist: numpy>=1.17
Requires-Dist: scipy>=1.2
Requires-Dist: h5py>=2.9
Requires-Dist: vtk>=8.1
Requires-Dist: matplotlib>=3.0
Requires-Dist: pyyaml>=3.12
